sites_faciles/__init__.py
sites_faciles/apps.py
sites_faciles/config/__init__.py
sites_faciles/config/settings.py
sites_faciles/config/settings_test.py
sites_faciles/config/urls.py
sites_faciles/config/wsgi.py
sites_faciles/locale/fr/LC_MESSAGES/django.mo
sites_faciles/locale/fr/LC_MESSAGES/django.po
sites_faciles/migrations/__init__.py
sites_faciles/static/sites-faciles/artwork/coding.svg
sites_faciles/static/sites-faciles/artwork/coding.svg.2024_05_13_23_27_03.0.svg
sites_faciles/static/sites-faciles/artwork/logo-republique.svg
sites_faciles/static/sites-faciles/artwork/logo.svg
sites_faciles/static/sites-faciles/artwork/technical-error.svg
sites_faciles/static/sites-faciles/artwork/web-logo-square.jpg
sites_faciles/static/sites-faciles/artwork/web-logo-white-square.svg
sites_faciles/static/sites-faciles/css/admin.css
sites_faciles/static/sites-faciles/css/icon-picker.css
sites_faciles/static/sites-faciles/css/style.css
sites_faciles/static/sites-faciles/css/style.css.map
sites_faciles/static/sites-faciles/css/style2.sass
sites_faciles/static/sites-faciles/favicon/android-chrome-192x192.png
sites_faciles/static/sites-faciles/favicon/android-chrome-512x512.png
sites_faciles/static/sites-faciles/favicon/apple-touch-icon.png
sites_faciles/static/sites-faciles/favicon/favicon-16x16.png
sites_faciles/static/sites-faciles/favicon/favicon-32x32.png
sites_faciles/static/sites-faciles/favicon/favicon.ico
sites_faciles/static/sites-faciles/favicon/favicon.svg
sites_faciles/static/sites-faciles/favicon/lesgrandsvoisinscom.ico
sites_faciles/static/sites-faciles/favicon/manifest.webmanifest
sites_faciles/static/sites-faciles/favicon/site.webmanifest
sites_faciles/templates/404.html
sites_faciles/templates/500.html
sites_faciles/templates/base.html
sites_faciles/templates/sites_faciles/follow.html
sites_faciles/templates/sites_faciles/form_page.html
sites_faciles/templates/sites_faciles/form_page_landing.html
sites_faciles/templates/sites_faciles/heading.html
sites_faciles-0.0.2.dist-info/LICENSE
sites_faciles-0.0.2.dist-info/METADATA
sites_faciles-0.0.2.dist-info/WHEEL
sites_faciles-0.0.2.dist-info/RECORD
