Metadata-Version: 2.1
Name: sites-faciles
Version: 0.0.2
Summary: Gestionnaire de contenu permettant de créer et gérer un site internet basé sur le Système de design de l'État, accessible et responsive
Home-page: https://github.com/chris2fr/sites-faciles
Keywords: wagtail
Author: Chris Mann
Author-email: chris@mann.fr
Maintainer: Chris Mann
Maintainer-email: chris@mann.fr
Requires-Python: >=3.11,<4.0
Classifier: Development Status :: 4 - Beta
Classifier: Environment :: Web Environment
Classifier: Framework :: Django
Classifier: Framework :: Django :: 4.2
Classifier: Framework :: Django :: 5.0
Classifier: Framework :: Wagtail
Classifier: Framework :: Wagtail :: 5
Classifier: Framework :: Wagtail :: 6
Classifier: Intended Audience :: Developers
Classifier: License :: OSI Approved :: MIT License
Classifier: Operating System :: OS Independent
Classifier: Programming Language :: Python :: 3
Classifier: Programming Language :: Python :: 3.11
Classifier: Programming Language :: Python :: 3.12
Classifier: Programming Language :: Python :: 3.13
Classifier: Topic :: Internet :: WWW/HTTP :: Dynamic Content
Classifier: Topic :: Software Development :: Libraries
Classifier: Topic :: Utilities
Requires-Dist: beautifulsoup4 (>=4.12.3,<5.0.0)
Requires-Dist: boto3 (>=1.34.56,<2.0.0)
Requires-Dist: dj-database-url (>=2.1.0,<3.0.0)
Requires-Dist: dj-static (>=0.0.6,<0.0.7)
Requires-Dist: django (>=5.0.6,<6.0.0)
Requires-Dist: django-allauth (>=65.1.0,<66.0.0)
Requires-Dist: django-debug-toolbar (>=4.3.0,<5.0.0)
Requires-Dist: django-design-system (>=0.0.2,<0.0.3)
Requires-Dist: django-sass-processor (>=1.3,<2.0)
Requires-Dist: django-simple-captcha (>=0.6.0,<0.7.0)
Requires-Dist: django-storages[s3] (>=1.14.2,<2.0.0)
Requires-Dist: django-taggit (>=5.0.1,<6.0.0)
Requires-Dist: django_distill (>=3.1.3,<4.0.0)
Requires-Dist: gunicorn (>=22.0.0,<23.0.0)
Requires-Dist: libsass (>=0.22.0,<0.23.0)
Requires-Dist: psycopg2-binary (>=2.9.9,<3.0.0)
Requires-Dist: python-dotenv (>=1.0.0,<2.0.0)
Requires-Dist: python-keycloak (>=4.6.3,<5.0.0)
Requires-Dist: unidecode (>=1.3.8,<2.0.0)
Requires-Dist: wagtail (>=6.1.1,<7.0.0)
Requires-Dist: wagtail-design-system (>=0.0.2,<0.0.3)
Requires-Dist: wagtail-localize (>=1.9,<2.0)
Requires-Dist: wagtail-markdown (>=0.11.1,<0.12.0)
Requires-Dist: wagtail-modeladmin (>=2.0.0,<3.0.0)
Requires-Dist: wagtail-transfer (>=0.9.4,<0.10.0)
Requires-Dist: wagtailmenus (>=4.0,<5.0)
Project-URL: Repository, https://github.com/chris2fr/sites-faciles/tree/sites-faciles
